ratcliff_breast_cancer_predictor/__init__.py
ratcliff_breast_cancer_predictor/model/cancer_predictor_model.sav
ratcliff_breast_cancer_predictor/predictor.py
ratcliff_breast_cancer_predictor/resources/breast-cancer-wisconsin.data
ratcliff_breast_cancer_predictor/resources/breast-cancer-wisconsin.names
ratcliff_breast_cancer_predictor-0.1.2.dist-info/METADATA
ratcliff_breast_cancer_predictor-0.1.2.dist-info/WHEEL
ratcliff_breast_cancer_predictor-0.1.2.dist-info/RECORD
