Metadata-Version: 2.1
Name: ratcliff-breast-cancer-predictor
Version: 0.1.2
Summary: 
Author: ryanratcliff
Author-email: ryanrratcliff@gmail.com
Requires-Python: >=3.11,<4.0
Classifier: Programming Language :: Python :: 3
Classifier: Programming Language :: Python :: 3.11
Requires-Dist: black (>=23.7.0,<24.0.0)
Requires-Dist: pandas (>=2.0.3,<3.0.0)
Requires-Dist: poethepoet (>=0.21.1,<0.22.0)
Requires-Dist: scikit-learn (>=1.3.0,<2.0.0)
